nn_error_metrics/__init__.py
nn_error_metrics/nn_error_metrics.py
nn_error_metrics-1.0.1.dist-info/METADATA
nn_error_metrics-1.0.1.dist-info/WHEEL
nn_error_metrics-1.0.1.dist-info/dependency_links.txt
nn_error_metrics-1.0.1.dist-info/top_level.txt
nn_error_metrics-1.0.1.dist-info/RECORD
