Metadata-Version: 2.1
Name: nn-error-metrics
Version: 1.0.1
Summary: A collection of neural network machine learning error metrics.
Home-page: https://github.com/arif-x/nn-error_metrics
Author: Ariffudin
Author-email: sudo.ariffudin@email.com
License: MIT
Project-URL: Source, https://github.com/arif-x/nn-error_metrics
Project-URL: Source Code, https://github.com/arif-x/nn-error_metrics
Keywords: nn neural-network metrics nn-error_metrics
Platform: UNKNOWN
Classifier: License :: OSI Approved :: MIT License
Classifier: Programming Language :: Python :: 3
Classifier: Programming Language :: Python :: 3.6
Classifier: Programming Language :: Python :: 3.7
Classifier: Programming Language :: Python :: 3.8
Classifier: Programming Language :: Python :: 3.9
Classifier: Programming Language :: Python :: 3.10
Classifier: Operating System :: OS Independent
Requires-Dist: numpy
